kong_admin/receivers.py
kong_admin/__init__.py
kong_admin/apps.py
kong_admin/widgets.py
kong_admin/contrib.py
kong_admin/admin.py
kong_admin/logic.py
kong_admin/views.py
kong_admin/validators.py
kong_admin/models.py
kong_admin/enums.py
kong_admin/factory.py
kong_admin/templates/kong_admin/action_button_admin_actions.html
kong_admin/templates/kong_admin/action_button_admin_change_list.html
kong_admin/templates/kong_admin/show_config.html
kong_admin/migrations/__init__.py
kong_admin/migrations/0005_auto_20150922_1258.py
kong_admin/migrations/0001_initial.py
kong_admin/migrations/0003_auto_20150909_0756.py
kong_admin/migrations/0006_auto_20150923_0818.py
kong_admin/migrations/0002_auto_20150827_0931.py
kong_admin/migrations/0004_auto_20150909_0826.py
kong_admin/sync/__init__.py
kong_admin/sync/consumers.py
kong_admin/sync/apis.py
kong_admin/sync/base.py
kong_admin/templatetags/__init__.py
kong_admin/templatetags/action_button_admin.py
django_kong_admin-0.4.0.dist-info/METADATA
django_kong_admin-0.4.0.dist-info/top_level.txt
django_kong_admin-0.4.0.dist-info/DESCRIPTION.rst
django_kong_admin-0.4.0.dist-info/metadata.json
django_kong_admin-0.4.0.dist-info/WHEEL
django_kong_admin-0.4.0.dist-info/RECORD
