Metadata-Version: 2.0
Name: django-kong-admin
Version: 0.4.0
Summary: A reusable Django App to manage a Kong service (http://getkong.org)
Home-page: https://github.com/vikingco/django-kong-admin
Author: Dirk Moors
Author-email: dirk.moors@vikingco.com
License: BSD
Keywords: django-kong-admin
Platform: UNKNOWN
Classifier: Development Status :: 3 - Alpha
Classifier: Framework :: Django
Classifier: Intended Audience :: Developers
Classifier: License :: OSI Approved :: BSD License
Classifier: Operating System :: Unix
Classifier: Operating System :: POSIX
Classifier: Operating System :: Microsoft :: Windows
Classifier: Natural Language :: English
Classifier: Programming Language :: Python :: 2
Classifier: Programming Language :: Python :: 2.7
Classifier: Programming Language :: Python :: 3
Classifier: Programming Language :: Python :: 3.3
Classifier: Programming Language :: Python :: 3.4
Requires-Dist: django (>=1.5.1)
Requires-Dist: django-environ (>=0.3.0)
Requires-Dist: django-jsonfield2 (==15.06.08)
Requires-Dist: django-enumfield (==1.2.1)
Requires-Dist: django-ace (==1.0.2)
Requires-Dist: wheel (==0.24.0)
Requires-Dist: python-kong (>=0.4.0)
Requires-Dist: pytz (>=2015.4)
Requires-Dist: enum34 (>=1.0.4)
